{"I5mJRLNDQHJcIYdhb1acrg==":"mirandamunoz-all.png","q5HjwQZmyzz3ZbYnHwn1/Q==":"4.jpeg","NZ4czhxIGpA8tdBEtV/1yQ==":"6.jpeg","R98GbbtMZxpJWw0YFhPpiw==":"1.jpeg","6wXukGu42jpll5/PJWm1fw==":"2.jpeg","h1l37zwdF3F6VnqUjLxBHw==":"5.jpeg","3d+bESF/inaJaFLJEX1AvA==":"mm-logo-black-1.png","+FXxd2HOH/FvsXTtiPBjng==":"63a62ea817e0e-771c7708-82c7-4ffb-b4f0-083221446f9f-1600x1600.jpg","1jDDiMMrhRsFh0xydEw1Zw==":"63a62ea817e0e-771c7708-82c7-4ffb-b4f0-083221446f9f-1187x1600.jpg","TYrt969cJTM8bNvTnfW7fg==":"20230101-2959-121x702.jpeg","tvGAZmt8UKla7DtfoOR9Dw==":"63a62ea817e0e-771c7708-82c7-4ffb-b4f0-083221446f9f-1600x1600%20(1)-459x640.jpg","6RkGLmTqAAxtlkliYvdYgg==":"mbr-1920x1280.jpg"}